<?xml version="1.0" encoding="UTF-8"?><record_update sys_domain="global" table="sys_hub_flow">
    <sys_hub_flow action="DELETE">
        <access>public</access>
        <acls/>
        <active>false</active>
        <annotation/>
        <callable_by_client_api>false</callable_by_client_api>
        <category/>
        <compiler_build/>
        <copied_from/>
        <copied_from_name/>
        <description/>
        <internal_name>approvals</internal_name>
        <label_cache>[]</label_cache>
        <latest_snapshot/>
        <master_snapshot/>
        <name>Approvals</name>
        <natlang/>
        <outputs/>
        <remote_trigger_id/>
        <run_as>system</run_as>
        <run_with_roles/>
        <sc_callable>false</sc_callable>
        <show_draft_actions>false</show_draft_actions>
        <show_triggered_flows>false</show_triggered_flows>
        <status>draft</status>
        <sys_class_name>sys_hub_flow</sys_class_name>
        <sys_created_by>admin</sys_created_by>
        <sys_created_on>2021-02-10 10:24:28</sys_created_on>
        <sys_domain>global</sys_domain>
        <sys_domain_path>/</sys_domain_path>
        <sys_id>0236ac38079a201070cff9fc7c1ed0b7</sys_id>
        <sys_mod_count>0</sys_mod_count>
        <sys_name>Approvals</sys_name>
        <sys_overrides/>
        <sys_package display_value="Loaner" source="x_582560_loaner">a16172a40756201070cff9fc7c1ed083</sys_package>
        <sys_policy/>
        <sys_scope display_value="Loaner">a16172a40756201070cff9fc7c1ed083</sys_scope>
        <sys_update_name>sys_hub_flow_0236ac38079a201070cff9fc7c1ed0b7</sys_update_name>
        <sys_updated_by>admin</sys_updated_by>
        <sys_updated_on>2021-02-10 10:24:28</sys_updated_on>
        <type>flow</type>
    </sys_hub_flow>
    <sys_translated_text action="DELETE" query="documentkey=0236ac38079a201070cff9fc7c1ed0b7"/>
    <sys_variable_value action="DELETE" query="document_key=0236ac38079a201070cff9fc7c1ed0b7"/>
    <sys_flow_cat_variable_model action="DELETE" query="id=0236ac38079a201070cff9fc7c1ed0b7^sys_idNOT INce36ac38079a201070cff9fc7c1ed0b7"/>
    <sys_flow_cat_variable_model action="DELETE">
        <id>0236ac38079a201070cff9fc7c1ed0b7</id>
        <name>Approvals</name>
        <sys_created_by>admin</sys_created_by>
        <sys_created_on>2021-02-10 10:24:28</sys_created_on>
        <sys_id>ce36ac38079a201070cff9fc7c1ed0b7</sys_id>
        <sys_mod_count>0</sys_mod_count>
        <sys_scope/>
        <sys_updated_by>admin</sys_updated_by>
        <sys_updated_on>2021-02-10 10:24:28</sys_updated_on>
    </sys_flow_cat_variable_model>
    <sys_update_version action="INSERT_OR_UPDATE">
        <action>DELETE</action>
        <application display_value="Loaner">a16172a40756201070cff9fc7c1ed083</application>
        <file_path/>
        <instance_id>3e8729336fcff100ffcca9cc5d3ee4ec</instance_id>
        <instance_name>dev12377</instance_name>
        <name>sys_hub_flow_0236ac38079a201070cff9fc7c1ed0b7</name>
        <payload><![CDATA[<?xml version="1.0" encoding="UTF-8"?><record_update sys_domain="global" table="sys_hub_flow"><sys_hub_flow action="INSERT_OR_UPDATE"><access>public</access><acls/><active>false</active><annotation/><callable_by_client_api>false</callable_by_client_api><category/><compiler_build/><copied_from/><copied_from_name/><description/><internal_name>approvals</internal_name><label_cache>[]</label_cache><latest_snapshot/><master_snapshot/><name>Approvals</name><natlang/><outputs/><remote_trigger_id/><run_as>system</run_as><run_with_roles/><sc_callable>false</sc_callable><show_draft_actions>false</show_draft_actions><show_triggered_flows>false</show_triggered_flows><status>draft</status><sys_class_name>sys_hub_flow</sys_class_name><sys_created_by>admin</sys_created_by><sys_created_on>2021-02-10 10:24:28</sys_created_on><sys_domain>global</sys_domain><sys_domain_path>/</sys_domain_path><sys_id>0236ac38079a201070cff9fc7c1ed0b7</sys_id><sys_mod_count>0</sys_mod_count><sys_name>Approvals</sys_name><sys_overrides/><sys_package display_value="Loaner" source="x_582560_loaner">a16172a40756201070cff9fc7c1ed083</sys_package><sys_policy/><sys_scope display_value="Loaner">a16172a40756201070cff9fc7c1ed083</sys_scope><sys_update_name>sys_hub_flow_0236ac38079a201070cff9fc7c1ed0b7</sys_update_name><sys_updated_by>admin</sys_updated_by><sys_updated_on>2021-02-10 10:24:28</sys_updated_on><type>flow</type></sys_hub_flow><sys_translated_text action="delete_multiple" query="documentkey=0236ac38079a201070cff9fc7c1ed0b7"/><sys_variable_value action="delete_multiple" query="document_key=0236ac38079a201070cff9fc7c1ed0b7"/><sys_flow_cat_variable_model action="delete_multiple" query="id=0236ac38079a201070cff9fc7c1ed0b7^sys_idNOT INce36ac38079a201070cff9fc7c1ed0b7"/><sys_flow_cat_variable_model action="INSERT_OR_UPDATE"><id>0236ac38079a201070cff9fc7c1ed0b7</id><name>Approvals</name><sys_created_by>admin</sys_created_by><sys_created_on>2021-02-10 10:24:28</sys_created_on><sys_id>ce36ac38079a201070cff9fc7c1ed0b7</sys_id><sys_mod_count>0</sys_mod_count><sys_scope/><sys_updated_by>admin</sys_updated_by><sys_updated_on>2021-02-10 10:24:28</sys_updated_on></sys_flow_cat_variable_model></record_update>]]></payload>
        <payload_hash>-976730198</payload_hash>
        <record_name>Approvals</record_name>
        <reverted_from/>
        <source>256172a40756201070cff9fc7c1ed085</source>
        <source_table>sys_update_set</source_table>
        <state>previous</state>
        <sys_created_by>admin</sys_created_by>
        <sys_created_on>2021-02-10 10:24:28</sys_created_on>
        <sys_id>4236ec38079a201070cff9fc7c1ed08f</sys_id>
        <sys_mod_count>0</sys_mod_count>
        <sys_recorded_at>1778b7887f30000001</sys_recorded_at>
        <sys_updated_by>admin</sys_updated_by>
        <sys_updated_on>2021-02-10 10:24:28</sys_updated_on>
        <type>Flow</type>
        <update_guid>8a36ec38449a20104010f19f80ab3b8e</update_guid>
        <update_guid_history>8a36ec38449a20104010f19f80ab3b8e:-976730198</update_guid_history>
    </sys_update_version>
    <sys_metadata_delete action="INSERT_OR_UPDATE">
        <sys_audit_delete/>
        <sys_class_name>sys_metadata_delete</sys_class_name>
        <sys_created_by>admin</sys_created_by>
        <sys_created_on>2021-02-10 12:16:32</sys_created_on>
        <sys_db_object display_value="" name="sys_hub_flow">sys_hub_flow</sys_db_object>
        <sys_id>75d966cb88a44c209e8bb74c26bf2400</sys_id>
        <sys_metadata>0236ac38079a201070cff9fc7c1ed0b7</sys_metadata>
        <sys_mod_count>0</sys_mod_count>
        <sys_name>Approvals</sys_name>
        <sys_package display_value="Loaner" source="x_582560_loaner">a16172a40756201070cff9fc7c1ed083</sys_package>
        <sys_parent/>
        <sys_policy/>
        <sys_scope display_value="Loaner">a16172a40756201070cff9fc7c1ed083</sys_scope>
        <sys_scope_delete display_value="">14d869a476614d5c81d36bc42be02b10</sys_scope_delete>
        <sys_update_name>sys_hub_flow_0236ac38079a201070cff9fc7c1ed0b7</sys_update_name>
        <sys_update_version display_value="sys_hub_flow_0236ac38079a201070cff9fc7c1ed0b7">4236ec38079a201070cff9fc7c1ed08f</sys_update_version>
        <sys_updated_by>admin</sys_updated_by>
        <sys_updated_on>2021-02-10 12:16:32</sys_updated_on>
    </sys_metadata_delete>
</record_update>
